[
  {
    "id": 103000273423,
    "title": "Updated method to remote onto Nisbets sites",
    "text": "Please find the attached document from Nisbets that explains setup of remote access to their sites as the previous IExplorer based method is now out of date. Initial contact to Nisbets IT will be required in order to setup dual authentication to log into their portal. Passwords can be found in lastpass.",
    "category": "INTERNAL Support Articles",
    "folder": "Nisbets",
    "created_at": "2024-02-06T09:36:23+00:00",
    "updated_at": "2024-02-06T09:40:56+00:00",
    "status": 2,
    "tags": [],
    "description": "<p dir=\"ltr\"><span dir=\"ltr\" style=\"font-size: 24px;\">Please find the attached document from Nisbets that explains setup of remote access to their sites as the previous IExplorer based method is now out of date.&nbsp;</span></p><p dir=\"ltr\"><br></p><p dir=\"ltr\"><span dir=\"ltr\" style=\"font-size: 24px;\">Initial contact &nbsp;to Nisbets IT will be required in order to setup dual authentication to log into their portal.</span></p><p dir=\"ltr\"><br></p><p dir=\"ltr\"><br></p><p dir=\"ltr\"><br></p><p dir=\"ltr\"><span dir=\"ltr\" style=\"font-size: 24px;\">Passwords can be found in lastpass.</span></p><p dir=\"ltr\"><br></p><p dir=\"ltr\"><br></p>",
    "user_id": 103081817424,
    "thumbs_up": 0,
    "thumbs_down": 1,
    "hits": 4,
    "seo_data": {},
    "modified_at": "2024-02-06T09:40:55+00:00",
    "modified_by": 103081817424
  }
]