[
  {
    "id": 103000299757,
    "title": "Omnis Installation Guide",
    "text": "The Omnis Installation Guide is attached to this Knowledge base article.",
    "category": "Omnis Customer Help",
    "folder": "Omnis Documentation",
    "created_at": "2024-06-25T10:43:24+01:00",
    "updated_at": "2024-06-25T10:43:24+01:00",
    "status": 2,
    "tags": [],
    "description": "<p dir=\"ltr\">The Omnis Installation Guide is attached to this Knowledge base article.</p>",
    "user_id": 103093502676,
    "thumbs_up": 0,
    "thumbs_down": 0,
    "hits": 0,
    "seo_data": {},
    "modified_at": "2024-06-25T10:43:24+01:00",
    "modified_by": 103093502676
  },
  {
    "id": 103000299758,
    "title": "Omnis Material Control Manual Vol 1",
    "text": "The Omnis Material Control Manual Vol 1 is attached to this Knowledge base article.",
    "category": "Omnis Customer Help",
    "folder": "Omnis Documentation",
    "created_at": "2024-06-25T10:46:41+01:00",
    "updated_at": "2024-06-25T10:46:42+01:00",
    "status": 2,
    "tags": [],
    "description": "<p dir=\"ltr\">The Omnis Material Control Manual Vol 1 is attached to this Knowledge base article.</p>",
    "user_id": 103093502676,
    "thumbs_up": 0,
    "thumbs_down": 0,
    "hits": 0,
    "seo_data": {},
    "modified_at": "2024-06-25T10:46:42+01:00",
    "modified_by": 103093502676
  },
  {
    "id": 103000299760,
    "title": "Omnis Material Control Manual Vol 2",
    "text": "The Omnis Material Control Manual Vol 2 is attached to this Knowledge base article.",
    "category": "Omnis Customer Help",
    "folder": "Omnis Documentation",
    "created_at": "2024-06-25T10:47:56+01:00",
    "updated_at": "2024-06-25T10:47:58+01:00",
    "status": 2,
    "tags": [],
    "description": "<p dir=\"ltr\">The Omnis Material Control Manual Vol 2 is attached to this Knowledge base article.</p>",
    "user_id": 103093502676,
    "thumbs_up": 0,
    "thumbs_down": 0,
    "hits": 0,
    "seo_data": {},
    "modified_at": "2024-06-25T10:47:58+01:00",
    "modified_by": 103093502676
  },
  {
    "id": 103000299761,
    "title": "Omnis Production Control Manual Vol 1",
    "text": "The Omnis Production Control Manual Vol 1 is attached to this Knowledge base article.",
    "category": "Omnis Customer Help",
    "folder": "Omnis Documentation",
    "created_at": "2024-06-25T10:50:01+01:00",
    "updated_at": "2024-06-25T10:50:03+01:00",
    "status": 2,
    "tags": [],
    "description": "<p dir=\"ltr\">The Omnis Production Control Manual Vol 1 is attached to this Knowledge base article.</p>",
    "user_id": 103093502676,
    "thumbs_up": 0,
    "thumbs_down": 0,
    "hits": 0,
    "seo_data": {},
    "modified_at": "2024-06-25T10:50:03+01:00",
    "modified_by": 103093502676
  },
  {
    "id": 103000299762,
    "title": "Omnis Production Control Manual Vol 2",
    "text": "The Omnis Production Control Manual Vol 2 is attached to this Knowledge base article.",
    "category": "Omnis Customer Help",
    "folder": "Omnis Documentation",
    "created_at": "2024-06-25T10:51:12+01:00",
    "updated_at": "2024-06-25T10:51:32+01:00",
    "status": 2,
    "tags": [],
    "description": "<p dir=\"ltr\">The Omnis Production Control Manual Vol 2 is attached to this Knowledge base article.</p>",
    "user_id": 103093502676,
    "thumbs_up": 0,
    "thumbs_down": 0,
    "hits": 0,
    "seo_data": {},
    "modified_at": "2024-06-25T10:51:32+01:00",
    "modified_by": 103093502676
  },
  {
    "id": 103000312013,
    "title": "Omnis V9.924 Hardware and Software Requirements Sept 2024",
    "text": "Omnis Hardware and Software Requirements The following hardware and software recommendations are made by K3 based on the experience of our customers and the operating system author’s recommendations. These requirements are effective as of September 2024 and are subject to change without notice. Minimum Hardware and Software Requirements Server Hardware Minimum Recommended Processor Speed Single Core 2ghz Dual Core 2ghz or greater Memory 1GB 2GB or greater Hard Disk (Free Space) SATA 7200rpm RAID-5 (SAS) Network Adapter 100 Base-T 1000 Base-T Important Notes Tape Backup and UPS (battery backup) highly recommended Hardware must comply with operating system author’s hardware compatibility list. Hardware specifications are based on a dedicated server and 20 concurrent users, if the server has additional workloads placed upon it, they should be factored into these recommendations. Server Software Supported Server Operating Systems Windows 2022 server Windows 2019 server Windows 2016 server Important Notes We do not recommend Windows Small Business Server, for sites larger than 20 concurrent Omnis users. However please discuss with support if this is a requirement. Client Hardware Minimum Recommended Processor Speed 1GHz 2 GHz+ RAM 512MB 1GB+ Hard Disk (Free Space) 5GB 10GB Network Adaptor 100 Base-T 1000 Base-T Display Settings SVGA (1024x768) SVGA (1024 x 768 or greater) Other Hardware Requirements Hardware must comply with operating system author’s hardware compatibility list. Isolated power circuits with surge protection or UPS recommended. Client Software Supported Client Operating Systems Windows 10 Professional or Enterprise Windows 11 Professional or Enterprise Note: To use 64bit Windows clients you will require the appropriate option. Contact your account manager for details. Other Required Software Internet Explorer version 6.x or above.",
    "category": "Omnis Customer Help",
    "folder": "Omnis Documentation",
    "created_at": "2024-09-12T11:30:41+01:00",
    "updated_at": "2024-09-12T11:30:43+01:00",
    "status": 2,
    "tags": [],
    "description": "<p><strong>Omnis Hardware and Software Requirements</strong></p><p><strong>&nbsp;</strong></p><p>The following hardware and software recommendations are made by K3 based on the experience of our customers and the operating system author’s recommendations.</p><p>These requirements are effective as of September 2024 and are subject to change without notice.</p><h1>Minimum Hardware and Software Requirements&nbsp;</h1><table border=\"1\" cellpadding=\"0\" cellspacing=\"0\"><tbody><tr><td colspan=\"5\" width=\"100%\"><h2><strong>Server Hardware</strong></h2></td></tr><tr><td width=\"31.5%\"><p>&nbsp;</p></td><td colspan=\"2\" width=\"31.5%\"><p><strong>Minimum</strong></p></td><td colspan=\"2\" width=\"37%\"><p><strong>Recommended</strong></p></td></tr><tr><td width=\"31.5%\"><p>Processor Speed</p></td><td colspan=\"2\" width=\"31.5%\"><p>Single Core 2ghz</p></td><td colspan=\"2\" width=\"37%\"><p>Dual Core 2ghz or greater</p></td></tr><tr><td width=\"31.5%\"><p>Memory&nbsp;</p></td><td colspan=\"2\" width=\"31.5%\"><p>1GB</p></td><td colspan=\"2\" width=\"37%\"><p>2GB or greater</p></td></tr><tr><td width=\"31.5%\"><p>Hard Disk (Free Space)</p></td><td colspan=\"2\" width=\"31.5%\"><p>SATA 7200rpm</p></td><td colspan=\"2\" width=\"37%\"><p>RAID-5 (SAS)</p></td></tr><tr><td width=\"31.5%\"><p>Network Adapter</p></td><td colspan=\"2\" width=\"31.5%\"><p>100 Base-T</p></td><td colspan=\"2\" width=\"37%\"><p>1000 Base-T</p></td></tr><tr><td width=\"31.44758735440932%\"><h5>Important Notes</h5></td><td colspan=\"4\" width=\"68.55241264559068%\"><ul><li>Tape Backup and UPS (battery backup) highly recommended&nbsp;</li><li>Hardware must comply with operating system author’s hardware compatibility list.</li><li>Hardware specifications are based on a dedicated server and 20 concurrent users, if the server has additional workloads placed upon it, they should be factored into these recommendations.</li></ul></td></tr><tr><td colspan=\"5\" width=\"100%\"><h2><strong>Server Software</strong></h2></td></tr><tr><td width=\"31.44758735440932%\"><p>Supported Server Operating Systems</p></td><td colspan=\"4\" width=\"68.55241264559068%\"><ul><li>Windows 2022 server</li><li>Windows 2019 server</li><li>Windows 2016 server</li></ul></td></tr><tr><td width=\"31.44758735440932%\"><h5>Important Notes</h5></td><td colspan=\"4\" width=\"68.55241264559068%\"><ul><li>We do not recommend Windows Small Business Server, for sites larger than 20 concurrent Omnis users. However please discuss with support if this is a requirement.</li></ul></td></tr><tr><td colspan=\"5\" width=\"100%\"><h2><strong>Client Hardware</strong></h2></td></tr><tr><td colspan=\"2\" width=\"32.945091514143094%\"><p>&nbsp;</p></td><td colspan=\"2\" width=\"30.948419301164726%\"><h5><strong>Minimum</strong></h5></td><td width=\"36.10648918469218%\"><h5><strong>Recommended</strong></h5></td></tr><tr><td colspan=\"2\" width=\"32.945091514143094%\"><p>Processor Speed</p></td><td colspan=\"2\" width=\"30.948419301164726%\"><p>1GHz</p></td><td width=\"36.10648918469218%\"><p>2 GHz+</p></td></tr><tr><td colspan=\"2\" width=\"32.945091514143094%\"><p>RAM</p></td><td colspan=\"2\" width=\"30.948419301164726%\"><p>512MB</p></td><td width=\"36.10648918469218%\"><p>1GB+</p></td></tr><tr><td colspan=\"2\" width=\"32.945091514143094%\"><p>Hard Disk (Free Space)</p></td><td colspan=\"2\" width=\"30.948419301164726%\"><p>5GB</p></td><td width=\"36.10648918469218%\"><p>10GB</p></td></tr><tr><td colspan=\"2\" width=\"32.945091514143094%\"><p>Network Adaptor</p></td><td colspan=\"2\" width=\"30.948419301164726%\"><p>100 Base-T</p></td><td width=\"36.10648918469218%\"><p>1000 Base-T</p></td></tr><tr><td colspan=\"2\" width=\"32.945091514143094%\"><p>Display Settings</p></td><td colspan=\"2\" width=\"30.948419301164726%\"><p>SVGA (1024x768)</p></td><td width=\"36.10648918469218%\"><p>SVGA (1024 x 768 or greater)</p></td></tr><tr><td colspan=\"2\" width=\"32.945091514143094%\"><p>Other Hardware Requirements</p></td><td colspan=\"3\" width=\"67.0549084858569%\"><ul><li>Hardware must comply with operating system author’s hardware compatibility list.</li><li>Isolated power circuits with surge protection or UPS recommended.</li></ul></td></tr><tr><td colspan=\"5\" width=\"100%\"><h2><strong>Client Software</strong></h2></td></tr><tr><td colspan=\"2\" width=\"32.945091514143094%\"><p>Supported Client Operating Systems</p></td><td colspan=\"3\" width=\"67.0549084858569%\"><ul><li>Windows 10 Professional or Enterprise</li><li>Windows 11 Professional or Enterprise</li></ul><p>Note: To use 64bit Windows clients you will require the appropriate option. Contact your account manager for details.</p></td></tr><tr><td colspan=\"2\" width=\"32.945091514143094%\"><p>Other Required Software&nbsp;</p></td><td colspan=\"3\" width=\"67.0549084858569%\"><ul><li>Internet Explorer version 6.x or above.</li></ul></td></tr></tbody></table>",
    "user_id": 103093502676,
    "thumbs_up": 0,
    "thumbs_down": 0,
    "hits": 0,
    "seo_data": {},
    "modified_at": "2024-09-12T11:30:43+01:00",
    "modified_by": 103093502676
  },
  {
    "id": 103000312144,
    "title": "Omnis Client Installation",
    "text": "",
    "category": "Omnis Customer Help",
    "folder": "Omnis Documentation",
    "created_at": "2024-09-12T16:02:22+01:00",
    "updated_at": "2024-09-12T16:03:47+01:00",
    "status": 2,
    "tags": [],
    "description": "<p><img src=\"https://s3-eu-central-1.amazonaws.com/euc-cdn.freshdesk.com/data/helpdesk/attachments/production/103146235864/original/KHZmUNK5OSE46FJk-j2a4aXtb7kKSna4Vg.png?1726153406\" style=\"width: auto; max-width: 100%;\" class=\"fr-fic fr-fil fr-dib\" data-attachment=\"[object Object]\" data-id=\"103146235864\"></p>",
    "user_id": 103093502676,
    "thumbs_up": 0,
    "thumbs_down": 0,
    "hits": 0,
    "seo_data": {},
    "modified_at": "2024-09-12T16:03:47+01:00",
    "modified_by": 103093502676
  }
]